xbrl_forge/__init__.py
xbrl_forge/__main__.py
xbrl_forge/_version.py
xbrl_forge/logger_setup.py
xbrl_forge/file_conversion/BaseLoader.py
xbrl_forge/file_conversion/DocxLoader.py
xbrl_forge/file_conversion/__init__.py
xbrl_forge/schemas/input/wrapper.schema.json
xbrl_forge/schemas/input/general/xml-element.schema.json
xbrl_forge/schemas/input/reports/applied-tag.schema.json
xbrl_forge/schemas/input/reports/dimension.schema.json
xbrl_forge/schemas/input/reports/report.schema.json
xbrl_forge/schemas/input/reports/unit.schema.json
xbrl_forge/schemas/input/reports/content/all-contents.schema.json
xbrl_forge/schemas/input/reports/content/base-xbrl.schema.json
xbrl_forge/schemas/input/reports/content/image.schema.json
xbrl_forge/schemas/input/reports/content/list.schema.json
xbrl_forge/schemas/input/reports/content/paragraph.schema.json
xbrl_forge/schemas/input/reports/content/table.schema.json
xbrl_forge/schemas/input/reports/content/title.schema.json
xbrl_forge/schemas/input/taxonomies/element-labels.schema.json
xbrl_forge/schemas/input/taxonomies/entrypoint.schema.json
xbrl_forge/schemas/input/taxonomies/metadata.schema.json
xbrl_forge/schemas/input/taxonomies/role.schema.json
xbrl_forge/schemas/input/taxonomies/taxonomy-element.schema.json
xbrl_forge/schemas/input/taxonomies/taxonomy.schema.json
xbrl_forge/schemas/input/taxonomies/relationships/calculation.schema.json
xbrl_forge/schemas/input/taxonomies/relationships/definition.schema.json
xbrl_forge/schemas/input/taxonomies/relationships/presentation.schema.json
xbrl_forge/utils/__init__.py
xbrl_forge/utils/schema_validation.py
xbrl_forge/utils/tmp_dirs.py
xbrl_forge/webapi/__init__.py
xbrl_forge/xbrl_generation/BaseProducer.py
xbrl_forge/xbrl_generation/ContentDataclasses.py
xbrl_forge/xbrl_generation/ElementRender.py
xbrl_forge/xbrl_generation/HtmlProducer.py
xbrl_forge/xbrl_generation/HtmlTemplate.py
xbrl_forge/xbrl_generation/InputData.py
xbrl_forge/xbrl_generation/PackageDataclasses.py
xbrl_forge-0.0.16.dist-info/licenses/LICENCE.md
xbrl_forge-0.0.16.dist-info/METADATA
xbrl_forge-0.0.16.dist-info/WHEEL
xbrl_forge-0.0.16.dist-info/top_level.txt
xbrl_forge-0.0.16.dist-info/RECORD
